compipe/__init__.py
compipe/cmd_enroller.py
compipe/cmd_wrapper.py
compipe/runtime_env.py
compipe/exception/__init__.py
compipe/exception/app_api_error.py
compipe/exception/env_error.py
compipe/exception/general_error.py
compipe/exception/general_warning.py
compipe/exception/io_error.py
compipe/exception/task_queue_error.py
compipe/exception/user_access_error.py
compipe/exception/validate_error.py
compipe/response/__init__.py
compipe/response/command_result.py
compipe/response/response.py
compipe/unittest/__init__.py
compipe/unittest/cmd_test.py
compipe/utils/__init__.py
compipe/utils/access.py
compipe/utils/decorators.py
compipe/utils/decorators_exception_handler.py
compipe/utils/hash_code_helper.py
compipe/utils/io_helper.py
compipe/utils/logging.py
compipe/utils/mime_types.py
compipe/utils/parameters.py
compipe/utils/parser.py
compipe/utils/singleton.py
compipe/utils/task_queue.py
compipe/utils/task_queue_helper.py
compipe-0.2.22.dist-info/LICENSE
compipe-0.2.22.dist-info/METADATA
compipe-0.2.22.dist-info/WHEEL
compipe-0.2.22.dist-info/entry_points.txt
compipe-0.2.22.dist-info/top_level.txt
compipe-0.2.22.dist-info/RECORD
