Metadata-Version: 2.2
Name: compipe
Version: 0.2.22
Summary: a lite version of the command wrapper for python
Home-page: https://github.com/ImagineersHub/compipe
Author: esunvoteb
Author-email: esun@voteb.com
License: MIT
Keywords: python,command,commandlet,cmd,cmdlet
Classifier: Development Status :: 3 - Alpha
Classifier: Intended Audience :: Developers
Classifier: Topic :: Software Development :: Build Tools
Classifier: License :: OSI Approved :: MIT License
Classifier: Programming Language :: Python :: 3.7
Classifier: Programming Language :: Python :: 3.8
Classifier: Programming Language :: Python :: 3.9
License-File: LICENSE
Requires-Dist: requests>=2.28.2
Requires-Dist: cryptography>=36
Requires-Dist: tqdm>=4.63.0
Requires-Dist: wrapt>=1.13
Requires-Dist: google-api-python-client>=2.39
Requires-Dist: colorlog
Dynamic: author
Dynamic: author-email
Dynamic: classifier
Dynamic: description
Dynamic: description-content-type
Dynamic: home-page
Dynamic: keywords
Dynamic: license
Dynamic: requires-dist
Dynamic: summary
